fisp/__init__.py
fisp/fisp.py
fisp/pfisp.py
fisp-0.3.0.dist-info/LICENSE
fisp-0.3.0.dist-info/METADATA
fisp-0.3.0.dist-info/WHEEL
fisp-0.3.0.dist-info/top_level.txt
fisp-0.3.0.dist-info/RECORD
