Metadata-Version: 2.1
Name: fisp
Version: 0.3.0
Summary: FISP: a 1D Fast Ion Spectra Propagator for solid cold targets.
Author-email: Howel Larreur <hwlr33@gmail.com>
Project-URL: Homepage, https://pypi.org/project/fisp/
Keywords: simulation,spectrum,ion,target
Classifier: Programming Language :: Python :: 3
Classifier: License :: OSI Approved :: GNU General Public License v3 (GPLv3)
Classifier: Operating System :: OS Independent
Requires-Python: >=3.8
License-File: LICENSE
Requires-Dist: matplotlib
Requires-Dist: numpy
Requires-Dist: scipy
Requires-Dist: tqdm
